plone.app.users-3.1.4-py3.13-nspkg.pth
plone/app/users/TODO.txt
plone/app/users/__init__.py
plone/app/users/configure.zcml
plone/app/users/field_extender.py
plone/app/users/schema.py
plone/app/users/setuphandlers.py
plone/app/users/testing.py
plone/app/users/upgrades.py
plone/app/users/utils.py
plone/app/users/vocabularies.py
plone/app/users/browser/__init__.py
plone/app/users/browser/account-configlet.pt
plone/app/users/browser/account-panel.pt
plone/app/users/browser/account.py
plone/app/users/browser/configure.zcml
plone/app/users/browser/interfaces.py
plone/app/users/browser/memberregistration.pt
plone/app/users/browser/membersearch.py
plone/app/users/browser/membersearch_form.pt
plone/app/users/browser/newuser_form.pt
plone/app/users/browser/passwordpanel.py
plone/app/users/browser/personalpreferences.py
plone/app/users/browser/register.py
plone/app/users/browser/register_form.pt
plone/app/users/browser/registered.pt
plone/app/users/browser/registered.py
plone/app/users/browser/schema_layout.pt
plone/app/users/browser/schemaeditor.py
plone/app/users/browser/userdatapanel.py
plone/app/users/profiles/default/metadata.xml
plone/app/users/profiles/default/userschema.xml
plone/app/users/tests/__init__.py
plone/app/users/tests/base.py
plone/app/users/tests/duplicate_email.rst
plone/app/users/tests/email_login.rst
plone/app/users/tests/flexible_user_registration.rst
plone/app/users/tests/forms_navigationroot.rst
plone/app/users/tests/member_search.rst
plone/app/users/tests/onepixel.jpg
plone/app/users/tests/password.rst
plone/app/users/tests/personal_preferences.rst
plone/app/users/tests/personal_preferences_prefs_user_details.rst
plone/app/users/tests/plugins.rst
plone/app/users/tests/registration_forms.rst
plone/app/users/tests/test_account.py
plone/app/users/tests/test_doctests.py
plone/app/users/tests/test_exportimport.py
plone/app/users/tests/test_loginname_generator.py
plone/app/users/tests/test_member_search.py
plone/app/users/tests/test_new_user.py
plone_app_users-3.1.4.dist-info/METADATA
plone_app_users-3.1.4.dist-info/WHEEL
plone_app_users-3.1.4.dist-info/entry_points.txt
plone_app_users-3.1.4.dist-info/namespace_packages.txt
plone_app_users-3.1.4.dist-info/top_level.txt
plone_app_users-3.1.4.dist-info/RECORD
