Metadata-Version: 2.4
Name: plone.app.users
Version: 3.1.4
Summary: A package for all things users and groups related (specific to plone)
Home-page: https://pypi.org/project/plone.app.users
Author: Plone Foundation
Author-email: plone-developers@lists.sourceforge.net
License: GPL version 2
Keywords: Zope CMF Plone Users Groups
Classifier: Development Status :: 5 - Production/Stable
Classifier: Environment :: Web Environment
Classifier: Framework :: Plone
Classifier: Framework :: Plone :: 6.0
Classifier: Framework :: Plone :: Core
Classifier: Framework :: Zope :: 5
Classifier: License :: OSI Approved :: GNU General Public License v2 (GPLv2)
Classifier: Operating System :: OS Independent
Classifier: Programming Language :: Python
Classifier: Programming Language :: Python :: 3.8
Classifier: Programming Language :: Python :: 3.9
Classifier: Programming Language :: Python :: 3.10
Classifier: Programming Language :: Python :: 3.11
Requires-Python: >=3.8
Requires-Dist: Acquisition
Requires-Dist: Pillow
Requires-Dist: Products.GenericSetup
Requires-Dist: Products.PlonePAS>=5.0.1
Requires-Dist: Products.statusmessages
Requires-Dist: Zope
Requires-Dist: plone.autoform>=1.2
Requires-Dist: plone.app.event
Requires-Dist: plone.app.vocabularies
Requires-Dist: plone.base
Requires-Dist: plone.formwidget.namedfile>=1.0.3
Requires-Dist: plone.i18n
Requires-Dist: plone.memoize
Requires-Dist: plone.namedfile
Requires-Dist: plone.protect
Requires-Dist: plone.registry
Requires-Dist: plone.schema
Requires-Dist: plone.schemaeditor
Requires-Dist: plone.supermodel
Requires-Dist: plone.uuid
Requires-Dist: plone.z3cform
Requires-Dist: setuptools
Requires-Dist: z3c.form
Requires-Dist: zope.annotation
Requires-Dist: zope.cachedescriptors
Requires-Dist: zope.component
Requires-Dist: zope.event
Requires-Dist: zope.interface
Requires-Dist: zope.schema
Provides-Extra: test
Requires-Dist: Products.MailHost; extra == "test"
Requires-Dist: Products.PluggableAuthService; extra == "test"
Requires-Dist: plone.app.contenttypes[test]; extra == "test"
Requires-Dist: plone.app.multilingual; extra == "test"
Requires-Dist: plone.app.robotframework; extra == "test"
Requires-Dist: plone.app.testing; extra == "test"
Requires-Dist: plone.keyring; extra == "test"
Requires-Dist: plone.testing; extra == "test"
Dynamic: author
Dynamic: author-email
Dynamic: classifier
Dynamic: description
Dynamic: description-content-type
Dynamic: home-page
Dynamic: keywords
Dynamic: license
Dynamic: provides-extra
Dynamic: requires-dist
Dynamic: requires-python
Dynamic: summary
